dpy_firestore_manager/__init__.py
dpy_firestore_manager/client.py
dpy_firestore_manager/managers/__init__.py
dpy_firestore_manager/managers/database_manager.py
dpy_firestore_manager/managers/guild_manager.py
dpy_firestore_manager/managers/guilds_manager.py
dpy_firestore_manager/managers/member_manager.py
dpy_firestore_manager/managers/members_manager.py
dpy_firestore_manager/structures/__init__.py
dpy_firestore_manager/structures/collection.py
dpy_firestore_manager/structures/database.py
dpy_firestore_manager/structures/document.py
dpy_firestore_manager/utilities/__init__.py
dpy_firestore_manager/utilities/object.py
dpy_firestore_manager-0.0.1.dist-info/LICENSE
dpy_firestore_manager-0.0.1.dist-info/METADATA
dpy_firestore_manager-0.0.1.dist-info/WHEEL
dpy_firestore_manager-0.0.1.dist-info/top_level.txt
dpy_firestore_manager-0.0.1.dist-info/RECORD
