Metadata-Version: 2.1
Name: dpy-firestore-manager
Version: 0.0.1
Summary: Hello
Home-page: UNKNOWN
License: UNKNOWN
Platform: UNKNOWN
Requires-Dist: discord.py (>=1.0.1)
Requires-Dist: firebase-admin (>=5.0.0)
